mlflow_onesaitplatform_plugin-0.2.11-py3.7-nspkg.pth
onesaitplatformplugins/plugins.py
mlflow_onesaitplatform_plugin-0.2.11.dist-info/METADATA
mlflow_onesaitplatform_plugin-0.2.11.dist-info/WHEEL
mlflow_onesaitplatform_plugin-0.2.11.dist-info/entry_points.txt
mlflow_onesaitplatform_plugin-0.2.11.dist-info/namespace_packages.txt
mlflow_onesaitplatform_plugin-0.2.11.dist-info/top_level.txt
mlflow_onesaitplatform_plugin-0.2.11.dist-info/RECORD
