Metadata-Version: 2.1
Name: mlflow-onesaitplatform-plugin
Version: 0.2.11
Summary: Plugins for MLflow and Onesait Platform
Home-page: UNKNOWN
License: Apache v2.0
Keywords: onesaitplatform mlflow plugin
Platform: UNKNOWN
Requires-Dist: mlflow
Requires-Dist: onesaitplatform-client-services
